{
    "User": "taras240",
    "MemberSince": "2017-06-09 18:29:51",
    "LastActivity": {
        "ID": 0,
        "timestamp": null,
        "lastupdate": null,
        "activitytype": null,
        "User": "taras240",
        "data": null,
        "data2": null
    },
    "RichPresenceMsg": "Main Menu",
    "LastGameID": 470,
    "ContribCount": 0,
    "ContribYield": 0,
    "TotalPoints": 5745,
    "TotalSoftcorePoints": 1662,
    "TotalTruePoints": 12608,
    "Permissions": 1,
    "Untracked": 0,
    "ID": 42956,
    "UserWallActive": 1,
    "Motto": "",
    "Rank": 8234,
    "RecentlyPlayedCount": 3,
    "RecentlyPlayed": [
        {
            "GameID": 470,
            "ConsoleID": 3,
            "ConsoleName": "SNES/Super Famicom",
            "Title": "Super Bomberman",
            "ImageIcon": "/Images/043551.png",
            "ImageTitle": "/Images/039426.png",
            "ImageIngame": "/Images/039427.png",
            "ImageBoxArt": "/Images/069658.png",
            "LastPlayed": "Mon May 20 2024 22:50:12 GMT+0300 (за східноєвропейським літнім часом)",
            "AchievementsTotal": 54,
            "DateEarnedHardcore": "Mon May 20 2024 22:50:12 GMT+0300 (за східноєвропейським літнім часом)",
            "type": "newGame"
        }
    ],
    "Awarded": {
        "470": {
            "NumPossibleAchievements": 54,
            "PossibleScore": 474,
            "NumAchieved": 4,
            "ScoreAchieved": 18,
            "NumAchievedHardcore": 4,
            "ScoreAchievedHardcore": 18
        }
    },
    "RecentAchievements": [
        {
            "ID": 22473,
            "GameID": 470,
            "GameTitle": "Super Bomberman",
            "Title": "Inefficient Bomber",
            "Description": "Use more than 50 bombs in one stage as Player 1 (can be playing in 2 player mode)",
            "Points": 5,
            "Type": null,
            "BadgeName": "276685",
            "IsAwarded": "1",
            "DateAwarded": "Fri May 17 2024 00:13:02 GMT+0300 (за східноєвропейським літнім часом)",
            "HardcoreAchieved": 1,
            "DateEarnedHardcore": "Fri May 17 2024 00:13:02 GMT+0300 (за східноєвропейським літнім часом)",
            "type": "earnedAchivs",
            "BadgeURL": "Badge/276685.png"
        }
    ],
    "LastGame": {
        "ID": 470,
        "Title": "Super Bomberman",
        "ConsoleID": 3,
        "ConsoleName": "SNES/Super Famicom",
        "ForumTopicID": 24814,
        "Flags": 0,
        "ImageIcon": "/Images/043551.png",
        "ImageTitle": "/Images/039426.png",
        "ImageIngame": "/Images/039427.png",
        "ImageBoxArt": "/Images/069658.png",
        "Publisher": "Hudson Soft",
        "Developer": "Hudson Soft",
        "Genre": "Action, Puzzle",
        "Released": "April 28, 1993",
        "IsFinal": 0
    },
    "UserPic": "/UserPic/taras240.png",
    "TotalRanked": 60009,
    "Status": "Offline"
}